neuko/__init__.py
neuko/connection/__init__.py
neuko/connection/certificateManagement.py
neuko/connection/certificateStore.py
neuko/connection/connectionManagement.py
neuko/connection/connectionStore.py
neuko/connection/model.py
neuko/device/__init__.py
neuko/device/device.py
neuko/device/deviceManagement.py
neuko/device/identifierStore.py
neuko/device/model.py
neuko/device/telemetricState.py
neuko/device/telemetricWorker.py
neuko/iot/__init__.py
neuko/iot/azure.py
neuko/iot/bootstrap.py
neuko/iot/iot.py
neuko/iot/model.py
neuko/iot/neuko.py
neuko/lifecycle/__init__.py
neuko/lifecycle/connectionStateMachine.py
neuko/utility/__init__.py
neuko/utility/logger.py
neuko/utility/utils.py
neuko_device_sdk-1.2.0.dist-info/LICENSE
neuko_device_sdk-1.2.0.dist-info/METADATA
neuko_device_sdk-1.2.0.dist-info/WHEEL
neuko_device_sdk-1.2.0.dist-info/top_level.txt
neuko_device_sdk-1.2.0.dist-info/RECORD
