Metadata-Version: 2.1
Name: neuko-device-sdk
Version: 1.2.0
Summary: Neuko device SDK for Python hardware
Author: neuko.io
Author-email: hello@neuko.io
License: MIT
Keywords: iot,device,thing,cloud,mqtt,development,neuko
Classifier: Development Status :: 5 - Production/Stable
Classifier: Intended Audience :: Developers
Classifier: Topic :: Software Development :: Libraries :: Application Frameworks
Classifier: License :: OSI Approved :: MIT License
Classifier: Programming Language :: Python :: 3.6
Classifier: Programming Language :: Python :: 3.7
Classifier: Programming Language :: Python :: 3.8
Classifier: Programming Language :: Python :: 3.9
Classifier: Programming Language :: Python :: 3.10
License-File: LICENSE
Requires-Dist: aiodns
Requires-Dist: aiohttp
Requires-Dist: cchardet
Requires-Dist: paho-mqtt
Requires-Dist: pydash
Requires-Dist: python-dotenv
Requires-Dist: transitions
